ZtjShifting.py
picture_shifting-0.0.1.dist-info/METADATA
picture_shifting-0.0.1.dist-info/WHEEL
picture_shifting-0.0.1.dist-info/top_level.txt
picture_shifting-0.0.1.dist-info/RECORD
