Metadata-Version: 2.1
Name: picture-shifting
Version: 0.0.1
Summary: picture shifting
Home-page: https://github.com/ztj1993/py-picture-shifting
Author: ZhangTianJie
Author-email: ztj1993@gmail.com
License: MIT License
Keywords: picture shifting
Platform: UNKNOWN
Requires-Dist: numpy
Requires-Dist: opencv-python
